{
  "category": "metal_nut",
  "methods": {
    "CLIP": {
      "slope": 0.9978409064016293,
      "complexity_class": "O(N)",
      "description": "Linear",
      "avg_runtime_s": 0.6264663537343343,
      "n_samples": 3
    },
    "DINO": {
      "slope": 1.061956282476804,
      "complexity_class": "O(N)",
      "description": "Linear",
      "avg_runtime_s": 10.80133024851481,
      "n_samples": 3
    },
    "Hybrid": {
      "slope": 1.259111505400234,
      "complexity_class": "O(N^1.5)",
      "description": "Superlinear",
      "avg_runtime_s": 4.162781556447347,
      "n_samples": 3
    }
  }
}