{
  "category": "zipper",
  "methods": {
    "CLIP": {
      "slope": 0.9601752968042417,
      "complexity_class": "O(N)",
      "description": "Linear",
      "avg_runtime_s": 0.8603490193684896,
      "n_samples": 3
    },
    "DINO": {
      "slope": 1.0339648001899313,
      "complexity_class": "O(N)",
      "description": "Linear",
      "avg_runtime_s": 11.028065284093222,
      "n_samples": 3
    },
    "Hybrid": {
      "slope": 1.614174874896201,
      "complexity_class": "O(N^1.5)",
      "description": "Superlinear",
      "avg_runtime_s": 5.886662244796753,
      "n_samples": 3
    }
  }
}